{
  "timestamp": "2026-02-25T04:05:49.747289",
  "generated_code": "# Try/Except/Finally with Resource Recovery Pattern\n\nclass SecureBuffer:\n    _data: list[str]\n    _max_size: int\n    _is_cleaned: bool\n    \n    def __init__(self, max_size: int):\n        self._data = []\n        self._max_size = max_size\n        self._is_cleaned = False\n    \n    def append(self, item: str) -> None:\n        if len(self._data) >= self._max_size:\n            raise OverflowError(\"buffer full\")\n        self._data.append(item)\n    \n    def get_all(self) -> list[str]:\n        return self._data.copy()\n    \n    def cleanup(self) -> None:\n        self._is_cleaned = True\n        self._data.clear()\n\ndef process_items(buffer: SecureBuffer, items: list[str]) -> int:\n    processed: int = 0\n    \n    for item in items:\n        try:\n            buffer.append(item)\n            processed += 1\n        except OverflowError as e:\n            print(f\"overflow\")\n            break\n        except ValueError as e:\n            print(f\"invalid\")\n            continue\n        else:\n            print(f\"ok\")\n        finally:\n            pass\n    \n    return processed\n\ndef main():\n    buf: SecureBuffer = SecureBuffer(3)\n    \n    # Test 1: Normal operation within capacity\n    count: int = process_items(buf, [\"a\", \"b\"])\n    print(count)\n    \n    # Test 2: Overflow handling\n    buf2: SecureBuffer = SecureBuffer(2)\n    count2: int = process_items(buf2, [\"x\", \"y\", \"z\", \"w\"])\n    print(count2)\n\n# EXPECTED OUTPUT:\n# ok\n# ok\n# 2\n# ok\n# ok\n# overflow\n# 2",
  "expected_output": "ok\nok\n2\nok\nok\noverflow\n2\n",
  "actual_output": "ok\nok\n2\nok\nok\noverflow\n2",
  "feature_focus": "try_except_finally",
  "complexity": "medium",
  "backend_used": "klaude",
  "generation_duration": 86.04745292663574,
  "execution_duration": 4.594705104827881,
  "source_files": null
}