{
  "timestamp": "2026-03-10T12:56:48.711561",
  "skip_reason": "Sharpy compiler error after 3 attempts: Compilation errors:\n\nerror[SPY0224]: Function expects 1 arguments but got 0\n  --> /tmp/tmpsv4ra7_c/dogfood_test.spy:5:28\n    |\n  5 |         async for value in source():\n    |                            ^^^^^^^^\n    |\n\nerror[SPY0248]: Cannot override 'transform' because the base class method in 'AbstractStreamProcessor' is not marked @virtual or @abstract. Add @virtual to the method in the base class.\n  --> /tmp/tmpsv4ra7_c/dogfood_test.spy:28:5\n    |\n 28 |     async def transform(self, source: (int) -> int) -> int:\n    |     ^^^^^^^^^^^^^^^^^^^^^^^^^^^^^^^^^^^^^^^^^^^^^^^^^^^^^^^\n    |\n\nerror[SPY0224]: Function expects 1 arguments but got 0\n  --> /tmp/tmpsv4ra7_c/dogfood_test.spy:29:28\n    |\n 29 |         async for value in source():\n    |                            ^^^^^^^^\n    |\n\nerror[SPY0220]: Cannot pass argument of type '() -> IAsyncEnumerable[int]' to parameter of type '(int) -> int'\n  --> /tmp/tmpsv4ra7_c/dogfood_test.spy:46:42\n    |\n 46 |     async for val in processor.transform(source_a2.generator):\n    |                                          ^^^^^^^^^^^^^^^^^^^\n    |\n\nerror[SPY0220]: Cannot assign type 'IAsyncEnumerable[int]' to variable of type 'int'\n  --> /tmp/tmpsv4ra7_c/dogfood_test.spy:50:5\n    |\n 50 |     gen_b: int = source_b.generator()\n    |     ^^^^^^^^^^^^^^^^^^^^^^^^^^^^^^^^^\n    |\n\nerror[SPY0220]: Cannot assign type 'IAsyncEnumerable[int]' to variable of type 'int'\n  --> /tmp/tmpsv4ra7_c/dogfood_test.spy:51:5\n    |\n 51 |     gen_c: int = source_c.generator()\n    |     ^^^^^^^^^^^^^^^^^^^^^^^^^^^^^^^^^\n    |\n\n",
  "generated_code": "import asyncio\n\nclass AbstractStreamProcessor[T]:\n    async def transform(self, source: (T) -> T) -> T:\n        async for value in source():\n            await asyncio.sleep(0.001)\n            yield value * 2\n\nclass NumberSource:\n    start: int\n    step: int\n\n    def __init__(self, start: int, step: int) -> None:\n        self.start = start\n        self.step = step\n\n    async def generator(self) -> int:\n        current: int = self.start\n        count: int = 0\n        while count < 3:\n            await asyncio.sleep(0.001)\n            yield current\n            current += self.step\n            count += 1\n\nclass DoublingProcessor(AbstractStreamProcessor[int]):\n    @override\n    async def transform(self, source: (int) -> int) -> int:\n        async for value in source():\n            await asyncio.sleep(0.001)\n            yield value * 2\n\nasync def main() -> None:\n    source_a: NumberSource = NumberSource(1, 2)\n    source_b: NumberSource = NumberSource(10, 5)\n    source_c: NumberSource = NumberSource(100, 50)\n\n    print(\"Original:\")\n    async for val in source_a.generator():\n        print(val)\n\n    processor: DoublingProcessor = DoublingProcessor()\n    source_a2: NumberSource = NumberSource(1, 2)\n\n    print(\"Processed:\")\n    async for val in processor.transform(source_a2.generator):\n        print(val)\n\n    print(\"Merged:\")\n    gen_b: int = source_b.generator()\n    gen_c: int = source_c.generator()\n    async for val in gen_b:\n        print(val)\n    async for val in gen_c:\n        print(val)\n",
  "expected_output": "Original:\n1\n3\n5\nProcessed:\n2\n6\n10\nMerged:\n10\n15\n20\n100\n150\n200\n",
  "feature_focus": "async_generator",
  "complexity": "complex",
  "backend_used": "klaude",
  "generation_duration": 499.38619446754456,
  "source_files": null,
  "validation_output": null
}