{
  "timestamp": "2026-03-10T03:15:24.154724",
  "generated_code": "from geometry_base import Shape\nfrom geometry_shapes import Rectangle, Circle, calculate_total\n\ndef main():\n    # Create shapes from imported module\n    r1: Rectangle = Rectangle(\"R1\", 4.0, 5.0)\n    c1: Circle = Circle(\"C1\", 3.0)\n    \n    # Test individual area calculations\n    print(r1.get_area())\n    print(c1.get_area())\n    \n    # Test polymorphic method dispatch\n    print(r1.describe())\n    print(c1.describe())\n    \n    # Test utility function imported from module\n    shapes: list[Shape] = [r1, c1]\n    total: float = calculate_total(shapes)\n    print(total)\n",
  "expected_output": "20.0\n28.27431\nRectangle R1: 4.0 x 5.0 = 20.0\nCircle C1: r=3.0, area=28.27431\n48.27431\n",
  "actual_output": "20.0\n28.274309999999996\nRectangle R1: 4.0 x 5.0 = 20.0\nCircle C1: r=3.0, area=28.274309999999996\n48.27431",
  "feature_focus": "module_imports",
  "complexity": "medium",
  "backend_used": "klaude",
  "generation_duration": 363.1890585422516,
  "execution_duration": 5.298701763153076,
  "source_files": {
    "geometry_base.spy": "@abstract\nclass Shape:\n    name: str\n    \n    def __init__(self, name: str):\n        self.name = name\n    \n    @abstract\n    def get_area(self) -> float: ...\n    \n    @virtual\n    def describe(self) -> str:\n        return f\"Shape: {self.name}\"\n",
    "geometry_shapes.spy": "from geometry_base import Shape\n\nclass Rectangle(Shape):\n    width: float\n    height: float\n    \n    def __init__(self, name: str, width: float, height: float):\n        super().__init__(name)\n        self.width = width\n        self.height = height\n    \n    @override\n    def get_area(self) -> float:\n        return self.width * self.height\n    \n    @override\n    def describe(self) -> str:\n        return f\"Rectangle {self.name}: {self.width} x {self.height} = {self.get_area()}\"\n\nclass Circle(Shape):\n    radius: float\n    \n    def __init__(self, name: str, radius: float):\n        super().__init__(name)\n        self.radius = radius\n    \n    @override\n    def get_area(self) -> float:\n        return 3.14159 * self.radius * self.radius\n    \n    @override\n    def describe(self) -> str:\n        return f\"Circle {self.name}: r={self.radius}, area={self.get_area()}\"\n\ndef calculate_total(shapes: list[Shape]) -> float:\n    total: float = 0.0\n    for s in shapes:\n        total += s.get_area()\n    return total\n",
    "main.spy": "from geometry_base import Shape\nfrom geometry_shapes import Rectangle, Circle, calculate_total\n\ndef main():\n    # Create shapes from imported module\n    r1: Rectangle = Rectangle(\"R1\", 4.0, 5.0)\n    c1: Circle = Circle(\"C1\", 3.0)\n    \n    # Test individual area calculations\n    print(r1.get_area())\n    print(c1.get_area())\n    \n    # Test polymorphic method dispatch\n    print(r1.describe())\n    print(c1.describe())\n    \n    # Test utility function imported from module\n    shapes: list[Shape] = [r1, c1]\n    total: float = calculate_total(shapes)\n    print(total)\n"
  }
}