{
  "timestamp": "2026-03-07T03:29:00.320719",
  "skip_reason": "Sharpy compiler error after 3 attempts: Compilation errors:\n\nType errors:\nerror[SPY0220]: Cannot assign type 'object' to variable of type 'Dimension'\n  --> /tmp/tmpfvaot4nh/dogfood_test.spy:21:9\n    |\n 21 |         d: Dimension = other\n    |         ^^^^^^^^^^^^^^^^^^^^\n    |\n\nValidation errors:\nerror[SPY0322]: Decorators cannot be applied to module-level variable declarations. '@static' on 'widget_counter' is only valid inside a class or struct body.\n  --> /tmp/tmpfvaot4nh/dogfood_test.spy:66:1\n    |\n 66 | @static\n    | ^^^^^^^\n    |\n\nerror[SPY0455]: Class 'Dimension' defines '__eq__(self, other: object)' but not '__hash__'. The .NET equality contract requires both. Define '__hash__(self) -> int'.\n  --> /tmp/tmpfvaot4nh/dogfood_test.spy:18:5\n    |\n 18 |     def __eq__(self, other: object) -> bool:\n    |     ^^^^^^^^^^^^^^^^^^^^^^^^^^^^^^^^^^^^^^^^\n    |\n\n",
  "generated_code": "# Test complex struct patterns: composition and dunder methods\n# Using if-elif instead of match guards (guards not implemented)\n\nstruct Dimension:\n    width: float\n    height: float\n\n    def __init__(self, w: float, h: float):\n        self.width = w\n        self.height = h\n\n    def area(self) -> float:\n        return self.width * self.height\n\n    def __str__(self) -> str:\n        return f\"Dimension({self.width}, {self.height})\"\n\n    def __eq__(self, other: object) -> bool:\n        if not isinstance(other, Dimension):\n            return False\n        d: Dimension = other\n        return self.width == d.width and self.height == d.height\n\nstruct Position:\n    x: float\n    y: float\n\n    def __init__(self, x: float, y: float):\n        self.x = x\n        self.y = y\n\n    def distance_from_origin(self) -> float:\n        return (self.x ** 2.0 + self.y ** 2.0) ** 0.5\n\n    def __str__(self) -> str:\n        return f\"Position({self.x}, {self.y})\"\n\nstruct Widget:\n    pos: Position\n    size: Dimension\n    name: str\n    visible: bool\n\n    def __init__(self, pos: Position, size: Dimension, name: str):\n        self.pos = pos\n        self.size = size\n        self.name = name\n        self.visible = True\n\n    def hide(self) -> None:\n        self.visible = False\n\n    def show(self) -> None:\n        self.visible = True\n\n    def center(self) -> Position:\n        cx = self.pos.x + self.size.width / 2.0\n        cy = self.pos.y + self.size.height / 2.0\n        return Position(cx, cy)\n\n    def __str__(self) -> str:\n        status = \"visible\" if self.visible else \"hidden\"\n        return f\"Widget({self.name}, {self.pos}, {self.size}, {status})\"\n\n# Static counter using @static decorator\n@static\nwidget_counter: int = 0\n\ndef classify_size(dim: Dimension) -> str:\n    # No guard clauses in match - using if-elif instead\n    if dim.width < 10.0 and dim.height < 10.0:\n        return \"small\"\n    if dim.width > 100.0 or dim.height > 100.0:\n        return \"large\"\n    return \"medium\"\n\ndef optional_widget_check(w: Widget?) -> None:\n    if w is not None:\n        print(f\"Widget present: {w.name}\")\n    else:\n        print(\"No widget found\")\n\ndef create_widget_at(x: float, y: float, w: float, h: float, name: str) -> Widget:\n    # Access and modify the static counter\n    widget_counter += 1\n    return Widget(Position(x, y), Dimension(w, h), f\"{name}_{widget_counter}\")\n\ndef main():\n    # Test struct creation and methods\n    dim = Dimension(5.0, 3.0)\n    print(dim.area())\n\n    # Test nested struct operations\n    pos = Position(10.0, 20.0)\n    print(pos.distance_from_origin())\n\n    # Test struct composition in Widget\n    widget = Widget(pos, dim, \"button\")\n    center = widget.center()\n    print(center.x)\n    print(center.y)\n\n    # Test struct stored in optionals\n    widget_opt: Widget? = widget\n    optional_widget_check(widget_opt)\n    widget_opt = None()\n    optional_widget_check(widget_opt)\n\n    # Test global counter in struct factory\n    w1 = create_widget_at(0.0, 0.0, 50.0, 30.0, \"panel\")\n    w2 = create_widget_at(100.0, 100.0, 200.0, 150.0, \"window\")\n    print(w1.name)\n    print(w2.name)\n\n    # Test struct visibility state\n    print(widget.visible)\n    widget.hide()\n    print(widget.visible)\n    widget.show()\n    print(widget.visible)\n\n    # Test struct equality\n    dim2 = Dimension(5.0, 3.0)\n    dim3 = Dimension(8.0, 9.0)\n    print(dim == dim2)\n    print(dim == dim3)\n\n    # Test classification (using if-elif since guards not supported)\n    print(classify_size(dim))\n    print(classify_size(Dimension(150.0, 50.0)))\n    print(classify_size(Dimension(50.0, 50.0)))\n",
  "expected_output": "15.0\n22.360679774997898\n27.5\n21.5\nWidget present: button\nNo widget found\npanel_1\nwindow_2\nTrue\nFalse\nTrue\nTrue\nFalse\nTrue\nsmall\nlarge\nmedium\n",
  "feature_focus": "struct_definition",
  "complexity": "complex",
  "backend_used": "klaude",
  "generation_duration": 475.85896944999695,
  "source_files": null,
  "validation_output": null
}